deepspeed_vacc/__init__.py
deepspeed_vacc/adaptor.py
deepspeed_vacc/utils.py
deepspeed_vacc/deepspeed/__init__.py
deepspeed_vacc/deepspeed/accelerator/__init__.py
deepspeed_vacc/deepspeed/accelerator/real_accelerator.py
deepspeed_vacc/deepspeed/accelerator/vacc_accelerator.py
deepspeed_vacc-0.16.3.dist-info/METADATA
deepspeed_vacc-0.16.3.dist-info/WHEEL
deepspeed_vacc-0.16.3.dist-info/top_level.txt
deepspeed_vacc-0.16.3.dist-info/RECORD
